biome_js/__init__.py
biome_js/__main__.py
biome_js-2.3.11.data/scripts/biome
biome_js-2.3.11.dist-info/METADATA
biome_js-2.3.11.dist-info/WHEEL
biome_js-2.3.11.dist-info/licenses/LICENSE-APACHE
biome_js-2.3.11.dist-info/licenses/LICENSE-MIT
biome_js-2.3.11.dist-info/RECORD
