Metadata-Version: 2.4
Name: biome-js
Version: 2.3.11
Classifier: Environment :: Console
Classifier: Intended Audience :: Developers
Classifier: Operating System :: OS Independent
Classifier: Programming Language :: JavaScript
Classifier: Programming Language :: Rust
Classifier: Topic :: Software Development :: Quality Assurance
License-File: LICENSE-APACHE
License-File: LICENSE-MIT
Summary: A toolchain for web projects, aimed to provide functionalities to maintain them. Biome offers formatter and linter, usable via CLI and LSP.
Home-Page: https://biomejs.dev/
Author: Biome Developers and Contributors
License-Expression: MIT OR Apache-2.0
Requires-Python: >=3.8
